faker_news/__init__.py
faker_news/cli.py
faker_news/client.py
faker_news/provider.py
faker_news/setup.py
faker_news/store.py
faker_news/fixtures/example_news.json
faker_news-0.1.2.dist-info/METADATA
faker_news-0.1.2.dist-info/WHEEL
faker_news-0.1.2.dist-info/entry_points.txt
faker_news-0.1.2.dist-info/top_level.txt
faker_news-0.1.2.dist-info/RECORD
