Metadata-Version: 2.4
Name: faker-news
Version: 0.1.2
Summary: Faker provider for generating fake news content using OpenAI-compatible LLM APIs
Author-email: Chris Beaven <smileychris@gmail.com>
License: MIT
Project-URL: Homepage, https://github.com/smileychris/faker-news
Project-URL: Documentation, https://github.com/smileychris/faker-news#readme
Project-URL: Repository, https://github.com/smileychris/faker-news
Project-URL: Issues, https://github.com/smileychris/faker-news/issues
Keywords: faker,news,generator,llm,openai
Classifier: Development Status :: 3 - Alpha
Classifier: Intended Audience :: Developers
Classifier: License :: OSI Approved :: MIT License
Classifier: Programming Language :: Python :: 3
Classifier: Programming Language :: Python :: 3.8
Classifier: Programming Language :: Python :: 3.9
Classifier: Programming Language :: Python :: 3.10
Classifier: Programming Language :: Python :: 3.11
Classifier: Programming Language :: Python :: 3.12
Requires-Python: >=3.9
Requires-Dist: faker>=18.0.0
Requires-Dist: openai>=1.0.0
Requires-Dist: click>=8.0.0
Requires-Dist: keyring>=24.0.0
Requires-Dist: platformdirs>=3.0.0
Requires-Dist: yaspin>=3.0.0
Requires-Dist: simple-term-menu>=1.6.0
